{
  "timestamp": "2026-02-14T18:19:40.165Z",
  "from_agent": "Executor",
  "to_agent": "Coordinator",
  "reason": "Phase 4 implementation steps 6-8 completed and verified; canonical terminal-surface guidance aligned across targeted agent docs.",
  "data": {
    "recommendation": "Reviewer",
    "steps_completed": 3,
    "files_modified": [
      "agents/analyst.agent.md",
      "agents/architect.agent.md",
      "agents/archivist.agent.md",
      "agents/brainstorm.agent.md",
      "agents/cognition.agent.md",
      "agents/coordinator.agent.md",
      "agents/researcher.agent.md",
      "agents/revisionist.agent.md",
      "agents/skill-writer.agent.md",
      "agents/tdd-driver.agent.md",
      "agents/executor.agent.md",
      "agents/reviewer.agent.md",
      "agents/runner.agent.md",
      "agents/tester.agent.md",
      "agents/worker.agent.md"
    ],
    "next_steps": [
      "Reviewer to run cross-agent validation checks and confirm consistency against canonical mcp-usage terminal guidance."
    ]
  }
}