{
  "timestamp": "2026-02-15T20:20:03.042Z",
  "from_agent": "Reviewer",
  "to_agent": "Coordinator",
  "reason": "Step 7 review passed: behavioral contract validated and no regressions detected in interactive/headless surfaces.",
  "data": {
    "recommendation": "Tester",
    "steps_completed": 1,
    "files_modified": [],
    "verification": {
      "targeted_test": "npx vitest run src/__tests__/tools/interactive-terminal.test.ts",
      "result": "pass",
      "tests": {
        "passed": 41,
        "failed": 0
      }
    },
    "reindex_changes": {
      "languages_changed": false,
      "frameworks_changed": false,
      "files_delta": 0,
      "lines_delta": 0
    },
    "notes": [
      "Host-only GUI path fail-closed behavior validated",
      "Non-headless visible semantics represented and tested",
      "Approval-unless-allowlisted semantics validated",
      "Local/container observable parity covered by targeted tests",
      "Existing-instance attach/dispatch represented and tested"
    ]
  }
}