{
  "timestamp": "2026-02-04T03:05:47.255Z",
  "from_agent": "Tester",
  "to_agent": "Revisionist",
  "reason": "Test execution complete: 218/244 passing (89.3%). 26 failures are test implementation issues, NOT functionality bugs. Server: 15 failures in file-store-buildscripts.test.ts - mocks don't create actual workspace/plan files causing 'not found' errors (12), plus vi.mocked(exec) issues (3). Dashboard: 11 failures in build-scripts.test.tsx - GoalsTab tests fail on multiple Edit buttons (5), AddBuildScriptForm tests fail because form starts collapsed (6). Core functionality appears working - failures are fixable test issues.",
  "data": {
    "test_results_summary": "26 failures out of 244 tests",
    "server_failures": 15,
    "dashboard_failures": 11,
    "critical_issues": false,
    "fix_required": [
      "Fix file-store-buildscripts.test.ts mocks to create actual workspace/plan files",
      "Fix exec mock implementation for runBuildScript tests",
      "Fix GoalsTab tests to handle 2 Edit buttons (use getAllByRole)",
      "Fix AddBuildScriptForm tests to expand form before accessing fields"
    ]
  }
}