{
  "timestamp": "2026-02-15T00:47:34.875Z",
  "from_agent": "Reviewer",
  "to_agent": "Coordinator",
  "reason": "Final validation passed; all required acceptance checks succeeded. Step 11 status transition is blocked only by Phase 7 confirmation gate.",
  "data": {
    "recommendation": "Archivist",
    "steps_completed": 0,
    "files_modified": [],
    "blockers": [
      "Phase 7 confirmation required before step 11 can transition to done."
    ],
    "next_steps": [
      "Confirm Phase 7 (user confirmation gate) via memory_plan confirm.",
      "Mark step 11 done after confirmation.",
      "Proceed to Archivist to archive plan."
    ]
  }
}