{
  "flake_controls": {
    "retry_once_enabled": true,
    "retry_performed": false
  },
  "gate": {
    "annotations": [],
    "classification": "clean",
    "generated_at": "2026-02-15T07:06:08.302Z",
    "mode": "strict",
    "passed": true,
    "reason": "Strict gate passed with no blocking replay drift.",
    "retried": false,
    "status": "PASS",
    "summary": {
      "failed_scenarios": 0,
      "high_severity_drifts": 0,
      "low_severity_drifts": 0,
      "medium_severity_drifts": 0,
      "passed_scenarios": 6,
      "total_scenarios": 6
    },
    "triage_labels": [
      "replay",
      "clean",
      "gate:strict"
    ]
  },
  "report": {
    "comparison_json": ".replay-runs/phase5-repeat-1-1771139168284/comparison.json",
    "report_markdown": ".replay-runs/phase5-repeat-1-1771139168284/report.md"
  }
}
